{
  "last_updated": "2026-04-10T02:34:52.258551Z",
  "next_update": "tomorrow 06:30 UTC",
  "funds_monitored": 7,
  "funds_with_sec_filings": 7,
  "run_status": "COMPLETE",
  "errors": [],
  "validation_warnings": [
    "KKR: No March 2026 NAV yet (filed Feb 2026 data)",
    "Ares: No March 2026 NAV yet (expected ~Apr 28, 2026)",
    "Stonepeak: No March 2026 NAV yet",
    "Brookfield: Jan 2026 NAV from website (no official SEC source)",
    "Hamilton Lane: No new filings since Feb 2026",
    "Partners Group: No new filings since Mar 2026"
  ],
  "last_run": "2026-04-10T02:34:52.258551Z"
}