{
  "generated_at": "2026-05-26T13:16:58.204539Z",
  "period_days": 7,
  "changes": [
    {
      "date": "2026-05-26",
      "type": "daily_check",
      "fund_id": "all",
      "summary": "Daily SEC EDGAR check: no new monthly NAV or quarterly AUM data points across the 7 monitored funds. Latest figures already captured (ISQ Mar 31; KKR Apr 30; Ares Apr 30; Stonepeak Mar 31; Brookfield Q4 2025 NPORT-P; HL Q4 2025 NPORT-P; PG Q4 2025 NPORT-P / Feb 28 NAV)."
    },
    {
      "date": "2026-05-20",
      "type": "board_event",
      "fund_id": "ares_aci",
      "summary": "Ares Core Infrastructure Fund launched Q2 2026 quarterly tender offer (SC TO-I acc 0001104659-26-064505): up to 5.0% of outstanding shares (6,924,711 shares), priced at May 31, 2026 NAV (Valuation Date), expires June 18, 2026.",
      "source_url": "https://www.sec.gov/Archives/edgar/data/2031750/000110465926064505/0001104659-26-064505-index.htm"
    },
    {
      "date": "2026-05-15",
      "type": "regulatory_filing",
      "fund_id": "hamilton_lane_infra",
      "summary": "Hamilton Lane filed routine quarterly periodic Repurchase Offer notification (N-23C3A, acc 0001213900-26-057243). Repurchase period May 15 - June 15, 2026; 5% of Class I/Y/R outstanding shares at NAV on Repurchase Pricing Date.",
      "source_url": "https://www.sec.gov/Archives/edgar/data/2020510/000121390026057243/0001213900-26-057243-index.htm"
    },
    {
      "date": "2026-05-15",
      "type": "regulatory_filing",
      "fund_id": "isq_openinfra",
      "summary": "ISQ OpenInfra Co filed Q1 2026 10-Q (acc 0001213900-26-057486) for period ending Mar 31, 2026. Monthly NAV data through Mar 31, 2026 already captured from prior 8-K EX-99.1 filings.",
      "source_url": "https://www.sec.gov/Archives/edgar/data/2059924/000121390026057486/0001213900-26-057486-index.htm"
    },
    {
      "date": "2026-05-15",
      "type": "regulatory_filing",
      "fund_id": "stonepeak_plus",
      "summary": "Stonepeak-Plus filed Q1 2026 10-Q (acc 0002045458-26-000019) for period ending Mar 31, 2026.",
      "source_url": "https://www.sec.gov/Archives/edgar/data/2045458/000204545826000019/0002045458-26-000019-index.htm"
    },
    {
      "date": "2026-05-14",
      "type": "regulatory_filing",
      "fund_id": "ares_aci",
      "summary": "Ares Core Infrastructure Fund filed Q1 2026 10-Q (acc 0002031750-26-000032) for period ending Mar 31, 2026.",
      "source_url": "https://www.sec.gov/Archives/edgar/data/2031750/000203175026000032/0002031750-26-000032-index.htm"
    },
    {
      "date": "2026-05-13",
      "type": "regulatory_filing",
      "fund_id": "kkr_infra_conglomerate",
      "summary": "KKR Infrastructure Conglomerate filed Q1 2026 10-Q (acc 0001948056-26-000037) for period ending Mar 31, 2026.",
      "source_url": "https://www.sec.gov/Archives/edgar/data/1948056/000194805626000037/0001948056-26-000037-index.htm"
    },
    {
      "date": "2026-05-12",
      "type": "regulatory_filing",
      "fund_id": "partners_group_infra",
      "summary": "Partners Group Next Generation Infrastructure LLC filed Form N-2 (acc 0001398344-26-008943) \u2014 registration statement update.",
      "source_url": "https://www.sec.gov/Archives/edgar/data/1989393/000139834426008943/0001398344-26-008943-index.htm"
    },
    {
      "date": "2026-05-07",
      "type": "subscription_event",
      "fund_id": "ares_aci",
      "summary": "Ares Core Infrastructure Fund preliminary May 2026 monthly closing of $712.6M (Class I/D/N/S) at April 30, 2026 NAV (acc 0002031750-26-000028). Subsequently finalized at $715.5M per 8-K filed 2026-05-19.",
      "source_url": "https://www.sec.gov/Archives/edgar/data/2031750/000203175026000028/0002031750-26-000028-index.htm"
    }
  ]
}