{
  "last_updated": "2026-04-01T16:05:08.644718+00:00",
  "funds": {
    "isq_openinfra": {
      "data_points_count": 4,
      "oldest_nav_date": "2025-10-01",
      "latest_nav_date": "2026-01-31",
      "return_1m": 4.32,
      "return_3m": 26.64,
      "return_ytd": 4.32,
      "return_itd": 26.64
    },
    "ares_aci": {
      "data_points_count": 16,
      "oldest_nav_date": "2024-11-30",
      "latest_nav_date": "2026-02-28",
      "return_1m": -0.4,
      "return_3m": -0.46,
      "return_6m": 0.38,
      "return_1y": -0.06,
      "return_ytd": -0.48,
      "return_itd": -1.91
    },
    "kkr_infra_conglomerate": {
      "data_points_count": 31,
      "oldest_nav_date": "2023-08-31",
      "latest_nav_date": "2026-02-28",
      "return_1m": 0.6,
      "return_3m": 0.97,
      "return_6m": 2.47,
      "return_1y": 5.4,
      "return_ytd": 1.07,
      "return_itd": 15.57
    },
    "stonepeak_plus": {
      "data_points_count": 10,
      "oldest_nav_date": "2025-05-31",
      "latest_nav_date": "2026-02-28",
      "return_1m": 0.51,
      "return_3m": 4.99,
      "return_6m": 9.33,
      "return_ytd": 2.02,
      "return_itd": 23.24
    },
    "brookfield_infra_income": {
      "data_points_count": 6,
      "oldest_nav_date": "2023-12-31",
      "latest_nav_date": "2026-01-31",
      "return_1m": 0.46,
      "return_3m": 4.79,
      "return_ytd": 0.46,
      "return_itd": 8.64
    },
    "hamilton_lane_infra": {
      "data_points_count": 3,
      "oldest_nav_date": "2024-09-30",
      "latest_nav_date": "2025-09-30",
      "return_1m": 7.63,
      "return_3m": 16.89,
      "return_itd": 16.89
    },
    "partners_group_infra": {
      "data_points_count": 4,
      "oldest_nav_date": "2024-03-31",
      "latest_nav_date": "2025-09-30",
      "return_1m": 4.68,
      "return_3m": 23.45,
      "return_itd": 23.45
    }
  }
}